hello_florin_package/__init__.py
hello_florin_package/hello.py
hello_florin_package-0.1.0.dist-info/METADATA
hello_florin_package-0.1.0.dist-info/WHEEL
hello_florin_package-0.1.0.dist-info/top_level.txt
hello_florin_package-0.1.0.dist-info/RECORD
