Metadata-Version: 2.1
Name: hello-florin-package
Version: 0.1.0
Summary: first_package
Home-page: UNKNOWN
Author: todorflorin196802
Author-email: todor.florin@gmail.com
License: UNKNOWN
Platform: UNKNOWN
